{
    "namespace": "TemplateCreateDialog",
    "CreateTemplate": {
        "description": "name your token",
        "en": "Name your template.",
        "de": "Benenne deine Vorlage."
    },
    "Name": {
        "description": "name field",
        "en": "Name",
        "de": "Name"
    },
    "Visibility": {
        "description": "visibility field",
        "en": "Visibility",
        "de": "Sichtbarkeit"
    },
    "Cancel": {
        "description": "cancel button",
        "en": "Cancel",
        "de": "Abbrechen"
    },
    "Confirm": {
        "description": "confirm button",
        "en": "Confirm",
        "de": "Bestätigen"
    },
    "FailedToLoadPermissions": {
        "description": "failed to load",
        "en": "Failed to load visibility options.",
        "de": "Sichtbarkeitseinstellungen konnten nicht geladen werden."
    }
}